isarsoft_model_utility/cli.py
isarsoft_model_utility/config.py
isarsoft_model_utility/exporter.py
isarsoft_model_utility/metadata.py
isarsoft_model_utility/thumbnail.svg
isarsoft_model_utility/utils.py
isarsoft_model_utility-0.0.4.dist-info/licenses/LICENSE
isarsoft_model_utility-0.0.4.dist-info/METADATA
isarsoft_model_utility-0.0.4.dist-info/WHEEL
isarsoft_model_utility-0.0.4.dist-info/entry_points.txt
isarsoft_model_utility-0.0.4.dist-info/top_level.txt
isarsoft_model_utility-0.0.4.dist-info/RECORD
