Metadata-Version: 2.4
Name: isarsoft-model-utility
Version: 0.0.4
Summary: Isarsoft Model Export Toolkit - Export models for Perception
Author-email: Sarthak Trivedi <sarthak.trivedi@isarsoft.com>
License: GPLv3.0
Project-URL: Homepage, https://isarsoft.com
Project-URL: Repository, https://gitlab.com/isarsoft/isarsoft-model-utility
Project-URL: Issues, https://gitlab.com/isarsoft/isarsoft-model-utility/issues
Keywords: onnx,object-detection,export,machine-learning,perception
Classifier: Development Status :: 4 - Beta
Classifier: Intended Audience :: Developers
Classifier: License :: OSI Approved :: GNU General Public License v3 (GPLv3)
Classifier: Programming Language :: Python :: 3.10
Classifier: Programming Language :: Python :: 3.11
Classifier: Topic :: Scientific/Engineering :: Artificial Intelligence
Classifier: Topic :: Software Development :: Libraries :: Python Modules
Requires-Python: >=3.8
License-File: LICENSE
Requires-Dist: torch>=1.13.0
Requires-Dist: onnx<=1.17.0
Requires-Dist: onnxruntime<=1.21.0
Requires-Dist: opencv-contrib-python-headless
Requires-Dist: numpy
Requires-Dist: Pillow
Requires-Dist: onnxslim
Requires-Dist: rfdetr-isarsoft[onnxexport]
Requires-Dist: tensorrt-yolo-isarsoft
Requires-Dist: ultralytics
Provides-Extra: dev
Requires-Dist: pytest; extra == "dev"
Requires-Dist: black; extra == "dev"
Requires-Dist: flake8; extra == "dev"
Requires-Dist: mypy; extra == "dev"
Dynamic: license-file
